llms_txt_rs-0.1.4.dist-info/METADATA
llms_txt_rs-0.1.4.dist-info/WHEEL
llms_txt_rs-0.1.4.dist-info/licenses/LICENSE
llms_txt_rs.libs/libgcc_s-1e52349c.so.1
llms_txt_rs/__init__.py
llms_txt_rs/llms_txt_rs.cpython-38-x86_64-linux-gnu.so
llms_txt_rs-0.1.4.dist-info/RECORD
