Metadata-Version: 2.3
Name: llms_txt_rs
Version: 0.1.4
Classifier: Programming Language :: Python
Classifier: Programming Language :: Python :: 3
Classifier: Programming Language :: Python :: 3 :: Only
Classifier: Programming Language :: Python :: 3.9
Classifier: Programming Language :: Python :: 3.10
Classifier: Programming Language :: Python :: 3.11
Classifier: Programming Language :: Python :: 3.12
Classifier: Programming Language :: Python :: 3.13
Classifier: Programming Language :: Rust
Classifier: Intended Audience :: Developers
Classifier: License :: OSI Approved :: Apache Software License
Classifier: Operating System :: POSIX :: Linux
Classifier: Operating System :: Microsoft :: Windows
Classifier: Operating System :: MacOS
Classifier: Typing :: Typed
License-File: LICENSE
Summary: Module for parsing llms.txt files
Home-Page: https://github.com/plaguss/llms-txt-rs
Author-email: Agustin Piqueres <agustin.piqueres@gmail.com>
License: Apache-2.0
Requires-Python: >=3.8
Project-URL: Homepage, https://github.com/plaguss/llms-txt-rs
Project-URL: Source, https://github.com/plaguss/llms-txt-rs
